Dockerfile
LICENSE
MANIFEST.in
README.md
disclaimer.txt
requirements.txt
setup.py
CoreMS.egg-info/PKG-INFO
CoreMS.egg-info/SOURCES.txt
CoreMS.egg-info/dependency_links.txt
CoreMS.egg-info/requires.txt
CoreMS.egg-info/top_level.txt
corems/__init__.py
corems/chroma_peak/__init__.py
corems/chroma_peak/calc/ChromaPeakCalc.py
corems/chroma_peak/calc/__init__.py
corems/chroma_peak/factory/__init__.py
corems/chroma_peak/factory/chroma_peak_classes.py
corems/encapsulation/__init__.py
corems/encapsulation/constant.py
corems/encapsulation/factory/__init__.py
corems/encapsulation/factory/parameters.py
corems/encapsulation/factory/processingSetting.py
corems/encapsulation/input/__init__.py
corems/encapsulation/input/parameter_from_json.py
corems/encapsulation/output/__init__.py
corems/encapsulation/output/parameter_to_dict.py
corems/encapsulation/output/parameter_to_json.py
corems/mass_spectra/__init__.py
corems/mass_spectra/calc/GC_Calc.py
corems/mass_spectra/calc/GC_Deconvolution.py
corems/mass_spectra/calc/GC_RI_Calibration.py
corems/mass_spectra/calc/MZSearch.py
corems/mass_spectra/calc/SignalProcessing.py
corems/mass_spectra/calc/__init__.py
corems/mass_spectra/calc/lc_calc.py
corems/mass_spectra/factory/GC_Class.py
corems/mass_spectra/factory/__init__.py
corems/mass_spectra/factory/chromat_data.py
corems/mass_spectra/factory/lc_class.py
corems/mass_spectra/input/__init__.py
corems/mass_spectra/input/andiNetCDF.py
corems/mass_spectra/input/boosterHDF5.py
corems/mass_spectra/input/brukerSolarix.py
corems/mass_spectra/input/corems_hdf5.py
corems/mass_spectra/input/massList.py
corems/mass_spectra/input/mzml.py
corems/mass_spectra/input/parserbase.py
corems/mass_spectra/input/rawFileReader.py
corems/mass_spectra/output/__init__.py
corems/mass_spectra/output/export.py
corems/mass_spectrum/__init__.py
corems/mass_spectrum/calc/AutoRecalibration.py
corems/mass_spectrum/calc/Calibration.py
corems/mass_spectrum/calc/CalibrationCalc.py
corems/mass_spectrum/calc/KendrickGroup.py
corems/mass_spectrum/calc/MassErrorPrediction.py
corems/mass_spectrum/calc/MassSpectrumCalc.py
corems/mass_spectrum/calc/MeanResolvingPowerFilter.py
