Metadata-Version: 2.1
Name: CoreMS
Version: 3.0.2
Summary: Mass Spectrometry Framework for Small Molecules Analysis
Home-page: https://github.com/EMSL-Computing/CoreMS
Author: Corilo, Yuri
Author-email: corilo@pnnl.gov
Classifier: License :: OSI Approved :: BSD License
Classifier: Programming Language :: Python :: 3.8
Classifier: Programming Language :: Python :: 3.9
Classifier: Programming Language :: Python :: 3.10
Classifier: Programming Language :: Python :: 3.11
Classifier: Development Status :: 4 - Beta
License-File: LICENSE
